core/__init__.py
core/__main__.py
core/cli.py
core/clipboard.py
core/fetch.py
core/parser.py
nuu_core-0.0.1.dist-info/METADATA
nuu_core-0.0.1.dist-info/WHEEL
nuu_core-0.0.1.dist-info/entry_points.txt
nuu_core-0.0.1.dist-info/licenses/LICENSE
nuu_core-0.0.1.dist-info/RECORD
