Metadata-Version: 2.4
Name: nuu-core
Version: 0.0.1
Summary: A CLI tool for fetching markdown content with linked documents
Project-URL: Homepage, https://github.com/NUU-Cognition/nuu-core
Project-URL: Bug Tracker, https://github.com/NUU-Cognition/nuu-core/issues
Project-URL: Repository, https://github.com/NUU-Cognition/nuu-core
Author-email: Nathan Luo <nathanluo13@gmail.com>
License: MIT
License-File: LICENSE
Keywords: cli,documentation,fetch,markdown
Classifier: Development Status :: 3 - Alpha
Classifier: Intended Audience :: Developers
Classifier: License :: OSI Approved :: MIT License
Classifier: Programming Language :: Python :: 3
Classifier: Programming Language :: Python :: 3.13
Classifier: Topic :: Software Development :: Documentation
Classifier: Topic :: Utilities
Requires-Python: >=3.13
Requires-Dist: click<8.2.0,>=8.0.0
Requires-Dist: pyperclip~=1.8.2
Requires-Dist: pyyaml~=6.0
Requires-Dist: typer~=0.12.0
